Q34/3.34TB.v
module Q34(Out_1,Out_2,Out_3,A,B,C,D);
input A,B,C,D;
output Out_1,Out_2,Out_3;

assign Out_1 = (A || !B) && (!C) && (C || D);
assign Out_2 = ((!C && D) || (B && C && D) || (C && !D)) && (!A || B);
assign Out_3 = (((A && B) || C) && D) || (!B && C);

endmodule

`timescale 1ns/1ps

module tb_Q34;
  // 1) Declare inputs as regs, outputs as wires
  reg  A, B, C, D;
  wire Out_1, Out_2, Out_3;

  // 2) Instantiate the Unit Under Test
  Q34 uut (
    .Out_1(Out_1),
    .Out_2(Out_2),
    .Out_3(Out_3),
    .A(A),
    .B(B),
    .C(C),
    .D(D)
  );

  // 3) VCD dump for GTKWave
  initial begin
    $dumpfile("tb_Q34.vcd");
    $dumpvars(0, tb_Q34);
  end

  // 4) Drive all input combinations and display results
  integer i;
  initial begin
    $display("\nTime | A B C D | Out_1 Out_2 Out_3");
    for (i = 0; i < 16; i = i + 1) begin
      {A, B, C, D} = i;      // MSB→LSB = A,B,C,D
      #10;                   // wait 10ns between vectors
      $display("%4dns | %b %b %b %b |   %b     %b      %b",
               $time, A, B, C, D, Out_1, Out_2, Out_3);
    end
    #10 $finish;             // end simulation
  end
endmodule

Q34/tb_Q34.vcd
$date
	Sun Jun 22 12:37:33 2025
$end
$version
	Icarus Verilog
$end
$timescale
	1ps
$end
$scope module tb_Q34 $end
$var wire 1 ! Out_3 $end
$var wire 1 " Out_2 $end
$var wire 1 # Out_1 $end
$var reg 1 $ A $end
$var reg 1 % B $end
$var reg 1 & C $end
$var reg 1 ' D $end
$var integer 32 ( i [31:0] $end
$scope module uut $end
$var wire 1 $ A $end
$var wire 1 % B $end
$var wire 1 & C $end
$var wire 1 ' D $end
$var wire 1 # Out_1 $end
$var wire 1 " Out_2 $end
$var wire 1 ! Out_3 $end
$upscope $end
$upscope $end
$enddefinitions $end
$comment Show the parameter values. $end
$dumpall
$end
#0
$dumpvars
b0 (
0'
0&
0%
0$
0#
0"
0!
$end
#10000
1"
1#
1'
b1 (
#20000
1!
0#
1&
0'
b10 (
#30000
0"
1'
b11 (
#40000
0!
1%
0&
0'
b100 (
#50000
1"
1'
b101 (
#60000
1&
0'
b110 (
#70000
1"
1!
1'
b111 (
#80000
0"
0!
1$
0%
0&
0'
b1000 (
#90000
1#
1'
b1001 (
#100000
1!
0#
1&
0'
b1010 (
#110000
1'
b1011 (
#120000
0!
1%
0&
0'
b1100 (
#130000
1"
1#
1!
1'
b1101 (
#140000
0#
0!
1&
0'
b1110 (
#150000
1"
1!
1'
b1111 (
#160000
b10000 (
